ecs_tasks_ops/__init__.py
ecs_tasks_ops/__main__.py
ecs_tasks_ops/ecs_conf.py
ecs_tasks_ops/ecs_data.py
ecs_tasks_ops/ecs_facade.py
ecs_tasks_ops/ecs_ssh.py
ecs_tasks_ops/pretty_json.py
ecs_tasks_ops/pretty_table.py
ecs_tasks_ops/py.typed
ecs_tasks_ops_qt5/__init__.py
ecs_tasks_ops_qt5/__main__.py
ecs_tasks_ops_qt5/about.py
ecs_tasks_ops_qt5/about.ui
ecs_tasks_ops_qt5/main_window.py
ecs_tasks_ops_qt5/mainwindow.ui
ecs_tasks_ops_qt5/qt5_ecs.py
ecs_tasks_ops_qt5/qt5_gui.py
ecs_tasks_ops_qt5/terminal.html
ecs_tasks_ops_qt5/terminal.js
ecs_tasks_ops_qt5/terminal.py
ecs_tasks_ops_qt5/xterm-addon-fit.js
ecs_tasks_ops_qt5/xterm-addon-web-links.js
ecs_tasks_ops_qt5/xterm.css
ecs_tasks_ops_qt5/xterm.js
ecs_tasks_ops-1.0.0.dist-info/LICENSE.rst
ecs_tasks_ops-1.0.0.dist-info/METADATA
ecs_tasks_ops-1.0.0.dist-info/WHEEL
ecs_tasks_ops-1.0.0.dist-info/entry_points.txt
ecs_tasks_ops-1.0.0.dist-info/RECORD
