Metadata-Version: 2.1
Name: ecs-tasks-ops
Version: 1.0.0
Summary: Ecs Tasks Ops
Home-page: https://github.com/ppalazon/ecs-tasks-ops
License: MIT
Author: Pablo Palazon
Author-email: ppalazon@antara.ws
Requires-Python: >=3.11.4,<4.0.0
Classifier: License :: OSI Approved :: MIT License
Classifier: Programming Language :: Python :: 3
Classifier: Programming Language :: Python :: 3.11
Requires-Dist: PyQt5 (>=5.15.9,<6.0.0)
Requires-Dist: PyQtWebEngine (>=5.15.6,<6.0.0)
Requires-Dist: boto3 (>=1.27.0,<2.0.0)
Requires-Dist: click (>=8.1.3,<9.0.0)
Requires-Dist: moto[ec2,ecs] (>=4.1.12,<5.0.0)
Requires-Dist: tabulate (>=0.9.0,<0.10.0)
Project-URL: Changelog, https://github.com/ppalazon/ecs-tasks-ops/releases
Project-URL: Documentation, https://ecs-tasks-ops.readthedocs.io
Project-URL: Repository, https://github.com/ppalazon/ecs-tasks-ops
